flixcrack/__init__.py
flixcrack/converter.py
flixcrack/errors.py
flixcrack/muxer.py
flixcrack/netflix.py
flixcrack/parser.py
flixcrack/utils.py
flixcrack/protos/__init__.py
flixcrack/protos/wv_proto2_pb2.py
flixcrack/protos/wv_proto3_pb2.py
flixcrack/types/__init__.py
flixcrack-2022.4.16.1.dist-info/LICENSE
flixcrack-2022.4.16.1.dist-info/METADATA
flixcrack-2022.4.16.1.dist-info/WHEEL
flixcrack-2022.4.16.1.dist-info/top_level.txt
flixcrack-2022.4.16.1.dist-info/RECORD
