Metadata-Version: 2.1
Name: flixcrack
Version: 2022.4.16.1
Summary: Netflix API Metadata & Downloader for Windows and Linux
Home-page: https://github.com/stefanodvx/flixcrack
Author: stefanodvx
Author-email: pp.stefanodvx@gmail.com
License: UNKNOWN
Project-URL: Tracker, https://github.com/stefanodvx/flixcrack/issues
Platform: UNKNOWN
Classifier: Programming Language :: Python :: 3
Classifier: Operating System :: OS Independent
Requires-Python: >=3.9.8
License-File: LICENSE
Requires-Dist: requests
Requires-Dist: protobuf
Requires-Dist: pycryptodomex
Requires-Dist: hyper
